imcautodeploy/10.10.20.yaml
imcautodeploy/ConfigInYAMLExample.yaml
imcautodeploy/DeploymentFunctions.py
imcautodeploy/__init__.py
imcautodeploy/autodeployBasedOnYAMLConfigFile.py
imcautodeploy/executeScriptWhenSomethingHappens.sh
imcautodeploy/verifyNewIMCAndInitializeImcAutoDeploy.py
imcautodeploy-0.1.8.dist-info/METADATA
imcautodeploy-0.1.8.dist-info/RECORD
imcautodeploy-0.1.8.dist-info/WHEEL
imcautodeploy-0.1.8.dist-info/top_level.txt
