Metadata-Version: 2.1
Name: imcautodeploy
Version: 0.1.8
Summary: This python package will configure a Cisco IMC server from nothing to fully functional
Home-page: http://github.com/ConsciaNorge/imcautodeploy
Author: Alexander Aasen
Author-email: alex_aasen@hotmail.com
License: MIT
Platform: UNKNOWN
Requires-Python: >=2.6,<2.8
Requires-Dist: imcsdk
Requires-Dist: PyYAML
